nepali_sentiment_analysis/NepaliNLP-sentiment.py
nepali_sentiment_analysis/__init__.py
nepali_sentiment_analysis/downloader.py
nepali_sentiment_analysis/nepali_sentiment_analysis.py
nepali_sentiment_analysis-1.0.dist-info/LICENSE.md
nepali_sentiment_analysis-1.0.dist-info/METADATA
nepali_sentiment_analysis-1.0.dist-info/WHEEL
nepali_sentiment_analysis-1.0.dist-info/top_level.txt
nepali_sentiment_analysis-1.0.dist-info/RECORD
