Metadata-Version: 2.1
Name: nepali-sentiment-analysis
Version: 1.0
Summary: UNKNOWN
Home-page: https://github.com/pudasainishushant/nepali_embedding
License: UNKNOWN
Platform: UNKNOWN
Classifier: Programming Language :: Python :: 3
Classifier: License :: OSI Approved :: MIT License
Classifier: Operating System :: OS Independent
Requires-Python: >=3.5
License-File: LICENSE.md
Requires-Dist: numpy (==1.22.1)
Requires-Dist: pandas (==1.4.0)
Requires-Dist: torch (==1.10.2)
Requires-Dist: scikit-learn
Requires-Dist: transformers (==4.16.1)
